ds82/__init__.py
ds82/module_01.py
ds82-0.0.3.dist-info/METADATA
ds82-0.0.3.dist-info/WHEEL
ds82-0.0.3.dist-info/RECORD
