Metadata-Version: 2.1
Name: ds82
Version: 0.0.3
Summary: my own utils
Author: Dmitry Drozdov
Author-email: ds.drozdov@gmail.com
Requires-Python: >=3.11,<4.0
Classifier: Programming Language :: Python :: 3
Classifier: Programming Language :: Python :: 3.11
Classifier: Programming Language :: Python :: 3.12
